lova/__init__.py
lova/aggregators/__init__.py
lova/aggregators/convert_label_encoding_to_vector.py
lova/aggregators/generate_sequence_order.py
lova/aggregators/merge_with_strength.py
lova/aggregators/normalize_with_percentile.py
lova/aggregators/reduce_with_binary_or.py
lova/dataloaders/__init__.py
lova/dataloaders/base.py
lova/dataloaders/download_hdfs.py
lova/dataloaders/load_config.py
lova/dataloaders/load_dataframe.py
lova/dataloaders/load_hdfs.py
lova/dataloaders/load_sequence.py
lova/dataloaders/logical_processors.py
lova/dataloaders/set_path.py
lova/dataset/__init__.py
lova/dataset/base.py
lova/dataset/movielens_100k.py
lova/evaluators/__init__.py
lova/evaluators/base.py
lova/evaluators/ials_evaluator.py
lova/preprocessors/__init__.py
lova/preprocessors/base.py
lova/preprocessors/preprocess_interactions.py
lova/recommenders/__init__.py
lova/recommenders/ials.py
lova-0.1.1.dist-info/LICENSE
lova-0.1.1.dist-info/METADATA
lova-0.1.1.dist-info/WHEEL
lova-0.1.1.dist-info/top_level.txt
lova-0.1.1.dist-info/RECORD
