Metadata-Version: 2.1
Name: lova
Version: 0.1.1
Summary: Lova (Long-term Value Algorithm) is a recommendation algorithm framework focused on long-term value matching.
Home-page: https://github.com/yinsn/Lova
Author: Yin Cheng
Author-email: yin.sjtu@gmail.com
Requires-Python: >=3.6
License-File: LICENSE
Requires-Dist: implicit >=0.7.2
Requires-Dist: joblib >=1.3.2
Requires-Dist: mpi4py >=3.1.5
Requires-Dist: optuna >=3.0.6
Requires-Dist: pyarrow >=14.0.1
Requires-Dist: pyyaml >=6.0
Requires-Dist: tqdm >=4.66.1
